url2markdown_cli/__init__.py
url2markdown_cli/__main__.py
url2markdown_cli/cli.py
url2markdown_cli-2024.10.3.dist-info/AUTHORS.md
url2markdown_cli-2024.10.3.dist-info/LICENSE
url2markdown_cli-2024.10.3.dist-info/METADATA
url2markdown_cli-2024.10.3.dist-info/WHEEL
url2markdown_cli-2024.10.3.dist-info/entry_points.txt
url2markdown_cli-2024.10.3.dist-info/top_level.txt
url2markdown_cli-2024.10.3.dist-info/RECORD
